mh_package/Birds.py
mh_package/TFS_api.py
mh_package/__init__.py
mh_package/module1.py
mh_package/tfs_process/__init__.py
mh_package/tfs_process/tfs_process.py
mh_package-0.18.dist-info/METADATA
mh_package-0.18.dist-info/WHEEL
mh_package-0.18.dist-info/top_level.txt
mh_package-0.18.dist-info/RECORD
