Metadata-Version: 2.1
Name: mh-package
Version: 0.18
Summary: My mh_package version
Home-page: https://job4moshe@dev.azure.com/job4moshe/mh_package/_git/mh_package
Author: Moshe Hayoun
Author-email: job4moshe@gmail.com
License: MIT
Platform: UNKNOWN
